Workbook

Sheet Sheet8

Sheet  Pivot
A1: Type | B1: Expense
A3: Row Labels | B3: Sum of Amount
A4: Bills | B4: 3950
A5: Entertainment | B5: 1598
A6: Food | B6: 19900
A7: Health | B7: 2350
A8: Savings | B8: 8000
A9: Shopping | B9: 5999
A10: Transport | B10: 5800
A11: Grand Total | B11: 47597

Sheet Transactions
A1: Date | B1: Category | C1: Sub-Category | D1: Description | E1: Type | F1: Amount | G1: Month
A2: 45292 | B2: Income | C2: Salary | D2: Monthly Salary | E2: Income | F2: 45000 | G2: =TEXT(A2,"MMM-YYYY") -> Jan-2024
A3: 45292 | B3: Food | C3: Groceries | D3: Big Bazaar | E3: Expense | F3: 3500 | G3: =TEXT(A3,"MMM-YYYY") -> Jan-2024
A4: 45293 | B4: Transport | C4: Fuel | D4: Petrol | E4: Expense | F4: 2000 | G4: =TEXT(A4,"MMM-YYYY") -> Jan-2024
A5: 45296 | B5: Food | C5: Restaurant | D5: Dinner Out | E5: Expense | F5: 1200 | G5: =TEXT(A5,"MMM-YYYY") -> Jan-2024
A6: 45298 | B6: Shopping | C6: Clothes | D6: New Shirt | E6: Expense | F6: 1500 | G6: =TEXT(A6,"MMM-YYYY") -> Jan-2024
A7: 45301 | B7: Bills | C7: Electricity | D7: Electric Bill | E7: Expense | F7: 800 | G7: =TEXT(A7,"MMM-YYYY") -> Jan-2024
A8: 45303 | B8: Bills | C8: Internet | D8: WiFi Bill | E8: Expense | F8: 500 | G8: =TEXT(A8,"MMM-YYYY") -> Jan-2024
A9: 45306 | B9: Food | C9: Groceries | D9: Weekly Shopping | E9: Expense | F9: 2800 | G9: =TEXT(A9,"MMM-YYYY") -> Jan-2024
A10: 45309 | B10: Transport | C10: Auto | D10: Office Commute | E10: Expense | F10: 600 | G10: =TEXT(A10,"MMM-YYYY") -> Jan-2024
A11: 45311 | B11: Entertainment | C11: OTT | D11: Netflix | E11: Expense | F11: 499 | G11: =TEXT(A11,"MMM-YYYY") -> Jan-2024
A12: 45313 | B12: Health | C12: Medicine | D12: Pharmacy | E12: Expense | F12: 350 | G12: =TEXT(A12,"MMM-YYYY") -> Jan-2024
A13: 45316 | B13: Shopping | C13: Electronics | D13: Earphones | E13: Expense | F13: 999 | G13: =TEXT(A13,"MMM-YYYY") -> Jan-2024
... A35: 45382 | B35: Bills | C35: Internet | D35: WiFi Bill | E35: Expense | F35: 500 | G35: =TEXT(A35,"MMM-YYYY") -> Mar-2024

Sheet Summary
A1: BUDGET SUMMARY
A3: Total Income | B3: =SUMIF(Transactions!E:E,"Income",Transactions!F:F) -> 143000
A4: Total Expense | B4: =SUMIF(Transactions!E:E,"Expense",Transactions!F:F) -> 47597
A5: Net Savings | B5: =B3-B4 -> 95403
A6: Savings % | B6: =B5/B3*100 -> 66.715385
A8: CATEGORY WISE
A9: Food | B9: =SUMIF(Transactions!B:B,"Food",Transactions!F:F) -> 19900
A10: Transport | B10: =SUMIF(Transactions!B:B,"Transport",Transactions!F:F) -> 5800
A11: Bills | B11: =SUMIF(Transactions!B:B,"Bills",Transactions!F:F) -> 3950
A12: Shopping | B12: =SUMIF(Transactions!B:B,"Shopping",Transactions!F:F) -> 5999
A13: Health | B13: =SUMIF(Transactions!B:B,"Health",Transactions!F:F) -> 2350
A14: Entertainment | B14: =SUMIF(Transactions!B:B,"Entertainment",Transactions!F:F) -> 1598
A15: Savings | B15: =SUMIF(Transactions!B:B,"Savings",Transactions!F:F) -> 8000
A17: COUNTS
A18: Total Transactions | B18: =COUNTA(Transactions!A:A)-1 -> 34
A19: Income Count | B19: =COUNTIF(Transactions!E:E,"Income") -> 4
A20: Expense Count | B20: =COUNTIF(Transactions!E:E,"Expense") -> 30
A22: AVERAGES
A23: Avg Income | B23: =AVERAGEIF(Transactions!E:E,"Income",Transactions!F:F) -> 35750
A24: Avg Expense | B24: =AVERAGEIF(Transactions!E:E,"Expense",Transactions!F:F) -> 1586.5667
A26: STATUS
A27: Savings Status | B27: =IF(B5>0,"✅ Saving Money","❌ Overspending") -> ✅ Saving Money
A28: Budget Health | B28: =IF(B6>=30,"Excellent",IF(B6>=20,"Good",IF(B6>=10,"Average","Poor"))) -> Excellent
A29: Alert | B29: =IF(OR(B9>15000,B12>8000),"⚠️ High Spending Alert","✅ Normal") -> ⚠️ High Spending Alert

Sheet Budget
A1: Category | B1: Budget | C1: Actual | D1: Difference | E1: Status
A2: Food | B2: 8000 | C2: =SUMIF(Transactions!B:B,A2,Transactions!F:F) -> 19900 | D2: =B2-D5 -> 9000 | E2: =IF(D2>=0,"✅ Under Budget","❌ Over Budget") -> ✅ Under Budget
A3: Transport | B3: 3000 | C3: =SUMIF(Transactions!B:B,A3,Transactions!F:F) -> 5800 | D3: =B3-D6 -> -20597 | E3: =IF(D3>=0,"✅ Under Budget","❌ Over Budget") -> ❌ Over Budget
A4: Bills | B4: 2500 | C4: =SUMIF(Transactions!B:B,A4,Transactions!F:F) -> 3950 | D4: =B4-D7 -> 1000 | E4: =IF(D4>=0,"✅ Under Budget","❌ Over Budget") -> ✅ Under Budget
A5: Shopping | B5: 4000 | C5: =SUMIF(Transactions!B:B,A5,Transactions!F:F) -> 5999 | D5: =B5-D8 -> -1000 | E5: =IF(D5>=0,"✅ Under Budget","❌ Over Budget") -> ❌ Over Budget
A6: Health | B6: 2000 | C6: =SUMIF(Transactions!B:B,A6,Transactions!F:F) -> 2350 | D6: =B6-D9 -> 23597 | E6: =IF(D6>=0,"✅ Under Budget","❌ Over Budget") -> ✅ Under Budget
A7: Entertainment | B7: 1500 | C7: =SUMIF(Transactions!B:B,A7,Transactions!F:F) -> 1598 | D7: =B7-D10 -> 1500 | E7: =IF(D7>=0,"✅ Under Budget","❌ Over Budget") -> ✅ Under Budget
A8: Savings | B8: 5000 | C8: =SUMIF(Transactions!B:B,A8,Transactions!F:F) -> 8000 | D8: =B8-D11 -> 5000 | E8: =IF(D8>=0,"✅ Under Budget","❌ Over Budget") -> ✅ Under Budget
A9: TOTAL | B9: =SUM(B2:B8) -> 26000 | C9: =SUM(C2:C8) -> 47597 | D9: =B9-C9 -> -21597

Sheet Lookup
A1: Category | B1: Budget | C1: Icon | E1: SEARCH | F1: Food
A2: Food | B2: 8000 | C2: 🍕 | E2: Category Name | F2: Food
A3: Transport | B3: 3000 | C3: 🚗 | E3: Budget Amount | F3: =VLOOKUP(F1,A2:C8,2,FALSE) -> 8000
A4: Bills | B4: 2500 | C4: 📱 | E4: Icon | F4: =VLOOKUP(F1,A2:C8,3,FALSE) -> 🍕
A5: Shopping | B5: 4000 | C5: 🛍️
A6: Health | B6: 2000 | C6: 💊 | E6: INDEX MATCH
A7: Entertainment | B7: 1500 | C7: 🎬 | E7: Budget Amount | F7: =INDEX(B2:B8,MATCH(F1,A2:A8,0)) -> 8000
A8: Savings | B8: 5000 | C8: 💰
A10: Month | B10: 45292 | C10: 45323 | D10: 45352 | E10: Find Month | F10: 45323
A11: Income | B11: 45000 | C11: 53000 | D11: 45000 | E11: Income | F11: =HLOOKUP(F10,A10:D11,2,FALSE) -> 53000

Sheet Dashboard
A1: 💰 Budget Tracker Dashboard 2024
